hangpy/__init__.py
hangpy/dtos/__init__.py
hangpy/dtos/server_configuration_dto.py
hangpy/entities/__init__.py
hangpy/entities/job.py
hangpy/entities/server.py
hangpy/enums/__init__.py
hangpy/enums/job_status.py
hangpy/repositories/__init__.py
hangpy/repositories/job_repository.py
hangpy/repositories/redis_job_repository.py
hangpy/repositories/redis_repository_base.py
hangpy/repositories/redis_server_repository.py
hangpy/repositories/server_repository.py
hangpy/services/__init__.py
hangpy/services/job_activity_base.py
hangpy/services/job_service.py
hangpy/services/log_service.py
hangpy/services/print_log_service.py
hangpy/services/server_service.py
hangpy/tests/__init__.py
hangpy/tests/fake.py
hangpy/tests/dtos/__init__.py
hangpy/tests/dtos/test_server_configuration_dto.py
hangpy/tests/entities/__init__.py
hangpy/tests/entities/test_job.py
hangpy/tests/entities/test_server.py
hangpy/tests/enums/__init__.py
hangpy/tests/enums/test_job_status.py
hangpy/tests/repositories/__init__.py
hangpy/tests/repositories/test_job_repository.py
hangpy/tests/repositories/test_redis_job_repository.py
hangpy/tests/repositories/test_redis_repository_base.py
hangpy/tests/repositories/test_redis_server_repository.py
hangpy/tests/repositories/test_server_repository.py
hangpy/tests/services/__init__.py
hangpy/tests/services/test_job_activity_base.py
hangpy/tests/services/test_job_service.py
hangpy/tests/services/test_log_service.py
hangpy/tests/services/test_print_log_service.py
hangpy/tests/services/test_server_service.py
hangpy-0.1.8.dist-info/LICENSE
hangpy-0.1.8.dist-info/METADATA
hangpy-0.1.8.dist-info/WHEEL
hangpy-0.1.8.dist-info/top_level.txt
hangpy-0.1.8.dist-info/RECORD
