Metadata-Version: 2.1
Name: hangpy
Version: 0.1.8
Summary: HangPy is a simple background job manager for Python
Home-page: https://github.com/luizfernandomeier/hangpy
Author: Luiz Fernando Meier
Author-email: luizfernandomeier@gmail.com
License: MIT
Platform: UNKNOWN
Classifier: Development Status :: 2 - Pre-Alpha
Classifier: Programming Language :: Python :: 3.9
Requires-Python: >=3.9
Requires-Dist: jsonpickle (>=2.0.0)
Requires-Dist: redis (>=3.5.3)
